demo.py
tablepic/__init__.py
tablepic/main.py
tablepic-0.2.1.dist-info/LICENSE
tablepic-0.2.1.dist-info/METADATA
tablepic-0.2.1.dist-info/WHEEL
tablepic-0.2.1.dist-info/top_level.txt
tablepic-0.2.1.dist-info/RECORD
