Metadata-Version: 2.1
Name: tablepic
Version: 0.2.1
Summary: A package can generate a picture which contains a table.
Author-email: Xin Yan <slash.xin@gmail.com>
Project-URL: Homepage, https://github.com/slash-xin/tablepic
Project-URL: Bug Tracker, https://github.com/slash-xin/tablepic/issues
Classifier: Programming Language :: Python :: 3
Classifier: License :: OSI Approved :: MIT License
Classifier: Operating System :: OS Independent
Requires-Python: >=3.6
License-File: LICENSE
